{
  "$schema": "https://raw.githubusercontent.com/spdx/spdx-spec/v2.2.1/schemas/spdx-schema.json",
  "spdxVersion": "SPDX-2.2",
  "dataLicense": "CC0-1.0",
  "SPDXID": "SPDXRef-DOCUMENT",
  "documentNamespace": "https://spdx.org/spdxdocs/boost-algorithm-x64-osx-1.82.0#2-d74b6d4b-6cb9-4a6d-a6b4-af76615fee1b",
  "name": "boost-algorithm:x64-osx@1.82.0#2 3e54ee6f359fff2ef981e04cbb9c61c56a1fd93006cf4247ff289d0de1eaf4bc",
  "creationInfo": {
    "creators": [
      "Tool: vcpkg-9990a4c9026811a312cb2af78bf77f3d9d288416"
    ],
    "created": "2023-09-11T22:22:42Z"
  },
  "relationships": [
    {
      "spdxElementId": "SPDXRef-port",
      "relationshipType": "GENERATES",
      "relatedSpdxElement": "SPDXRef-binary"
    },
    {
      "spdxElementId": "SPDXRef-port",
      "relationshipType": "CONTAINS",
      "relatedSpdxElement": "SPDXRef-file-0"
    },
    {
      "spdxElementId": "SPDXRef-port",
      "relationshipType": "CONTAINS",
      "relatedSpdxElement": "SPDXRef-file-1"
    },
    {
      "spdxElementId": "SPDXRef-binary",
      "relationshipType": "GENERATED_FROM",
      "relatedSpdxElement": "SPDXRef-port"
    },
    {
      "spdxElementId": "SPDXRef-file-0",
      "relationshipType": "CONTAINED_BY",
      "relatedSpdxElement": "SPDXRef-port"
    },
    {
      "spdxElementId": "SPDXRef-file-1",
      "relationshipType": "CONTAINED_BY",
      "relatedSpdxElement": "SPDXRef-port"
    }
  ],
  "packages": [
    {
      "name": "boost-algorithm",
      "SPDXID": "SPDXRef-port",
      "versionInfo": "1.82.0#2",
      "downloadLocation": "git+https://github.com/Microsoft/vcpkg#ports/boost-algorithm",
      "homepage": "https://github.com/boostorg/algorithm",
      "licenseConcluded": "BSL-1.0",
      "licenseDeclared": "NOASSERTION",
      "copyrightText": "NOASSERTION",
      "description": "Boost algorithm module",
      "comment": "This is the port (recipe) consumed by vcpkg."
    },
    {
      "name": "boost-algorithm:x64-osx",
      "SPDXID": "SPDXRef-binary",
      "versionInfo": "3e54ee6f359fff2ef981e04cbb9c61c56a1fd93006cf4247ff289d0de1eaf4bc",
      "downloadLocation": "NONE",
      "licenseConcluded": "BSL-1.0",
      "licenseDeclared": "NOASSERTION",
      "copyrightText": "NOASSERTION",
      "comment": "This is a binary package built by vcpkg."
    },
    {
      "SPDXID": "SPDXRef-resource-1",
      "name": "boostorg/algorithm",
      "downloadLocation": "git+https://github.com/boostorg/algorithm@boost-1.82.0",
      "licenseConcluded": "NOASSERTION",
      "licenseDeclared": "NOASSERTION",
      "copyrightText": "NOASSERTION",
      "checksums": [
        {
          "algorithm": "SHA512",
          "checksumValue": "46b49d336360fdaf6b3f28c93e4b4c6949d5b89ea4f718849ef40417811e32819b367513949a3040b343850698dac878a785639e18dc938066a1db9a07490ab6"
        }
      ]
    }
  ],
  "files": [
    {
      "fileName": ".//Users/liu/vcpkg/ports/boost-algorithm/portfile.cmake",
      "SPDXID": "SPDXRef-file-0",
      "checksums": [
        {
          "algorithm": "SHA256",
          "checksumValue": "96f257e6c4e84ecc28c2f392ce7c9b4f7ad42e1383e9c95b70e55fdf3beea375"
        }
      ],
      "licenseConcluded": "NOASSERTION",
      "copyrightText": "NOASSERTION"
    },
    {
      "fileName": ".//Users/liu/vcpkg/ports/boost-algorithm/vcpkg.json",
      "SPDXID": "SPDXRef-file-1",
      "checksums": [
        {
          "algorithm": "SHA256",
          "checksumValue": "9fe8a9e99d257d10df9166ccdec1b65bd1dafcf5408ff1e9887d2d371dfb18b9"
        }
      ],
      "licenseConcluded": "NOASSERTION",
      "copyrightText": "NOASSERTION"
    }
  ]
}
